{
  "schema_version": 1,
  "updated_at": "2026-05-16T00:07:59.837816Z",
  "snapshot_date": "2026-05-16",
  "source": "GitHub Actions weekly scan against Fabric warehouse",
  "duration_seconds": 127.940148,
  "totals": {
    "tables": 96,
    "rows": 1994850475,
    "tables_total_scanned": 231
  },
  "skipped_databases": [],
  "skipped_detail": [],
  "items": [
    {
      "database": "ReportingApplications",
      "schema": "dbo",
      "table": "leads",
      "rows": 400117203,
      "columns": 57
    },
    {
      "database": "ReportingCommunications",
      "schema": "dbo",
      "table": "Messages",
      "rows": 250962247,
      "columns": 26
    },
    {
      "database": "ReportingLoanbook",
      "schema": "dbo",
      "table": "Loan_History",
      "rows": 197794359,
      "columns": 24
    },
    {
      "database": "ReportingApplications",
      "schema": "dbo",
      "table": "ApplicationHistories",
      "rows": 105196702,
      "columns": 27
    },
    {
      "database": "ReportingCentralCrm",
      "schema": "dbo",
      "table": "GeneratedMessages",
      "rows": 97666020,
      "columns": 8
    },
    {
      "database": "ReportingTracking",
      "schema": "dbo",
      "table": "WebVisits",
      "rows": 93865481,
      "columns": 16
    },
    {
      "database": "ReportingApplications",
      "schema": "dbo",
      "table": "Tasks",
      "rows": 88393210,
      "columns": 9
    },
    {
      "database": "ReportingBrokers",
      "schema": "dbo",
      "table": "LeadScorecardScores",
      "rows": 86842440,
      "columns": 19
    },
    {
      "database": "ReportingApplications",
      "schema": "dbo",
      "table": "EventObjects",
      "rows": 81865851,
      "columns": 2
    },
    {
      "database": "ReportingApplications",
      "schema": "dbo",
      "table": "Events",
      "rows": 80442662,
      "columns": 9
    },
    {
      "database": "ReportingApplications",
      "schema": "dbo",
      "table": "LeadOutcomes",
      "rows": 46892534,
      "columns": 5
    },
    {
      "database": "ReportingCommunications",
      "schema": "dbo",
      "table": "Attachments",
      "rows": 45831408,
      "columns": 5
    },
    {
      "database": "ReportingPayments",
      "schema": "dbo",
      "table": "Events",
      "rows": 36534024,
      "columns": 16
    },
    {
      "database": "ReportingPayments",
      "schema": "dbo",
      "table": "EventObjects",
      "rows": 34737702,
      "columns": 2
    },
    {
      "database": "ReportingCommunications",
      "schema": "dbo",
      "table": "ShortUrls",
      "rows": 34523603,
      "columns": 10
    },
    {
      "database": "ReportingApplications",
      "schema": "dbo",
      "table": "Addresses",
      "rows": 33252236,
      "columns": 8
    },
    {
      "database": "ReportingApplications",
      "schema": "dbo",
      "table": "Telephones",
      "rows": 27817827,
      "columns": 5
    },
    {
      "database": "ReportingCreditbuilder",
      "schema": "dbo",
      "table": "Events",
      "rows": 25327559,
      "columns": 8
    },
    {
      "database": "ReportingApplications",
      "schema": "dbo",
      "table": "Emails",
      "rows": 21704223,
      "columns": 5
    },
    {
      "database": "ReportingApplications",
      "schema": "dbo",
      "table": "GovernmentIdentities",
      "rows": 17006952,
      "columns": 4
    },
    {
      "database": "ReportingApplications",
      "schema": "dbo",
      "table": "Customers",
      "rows": 16777577,
      "columns": 21
    },
    {
      "database": "ReportingLoanbook",
      "schema": "dbo",
      "table": "Events",
      "rows": 16715384,
      "columns": 9
    },
    {
      "database": "ReportingApplications",
      "schema": "dbo",
      "table": "Applications",
      "rows": 13635849,
      "columns": 31
    },
    {
      "database": "ReportingApplications",
      "schema": "dbo",
      "table": "ESignatures",
      "rows": 13507447,
      "columns": 22
    },
    {
      "database": "ReportingLookup",
      "schema": "dbo",
      "table": "Lookups",
      "rows": 12645588,
      "columns": 10
    },
    {
      "database": "ReportingCreditbuilder",
      "schema": "dbo",
      "table": "Transactions",
      "rows": 12396658,
      "columns": 11
    },
    {
      "database": "ReportingLoanbook",
      "schema": "dbo",
      "table": "Transactions",
      "rows": 11804847,
      "columns": 13
    },
    {
      "database": "ReportingApplications",
      "schema": "dbo",
      "table": "WebBehaviours",
      "rows": 9932994,
      "columns": 9
    },
    {
      "database": "ReportingBrokers",
      "schema": "dbo",
      "table": "PremiumLeadScores",
      "rows": 9559367,
      "columns": 10
    },
    {
      "database": "Whitebox",
      "schema": "dbo",
      "table": "ValidatedTels",
      "rows": 9124101,
      "columns": 7
    },
    {
      "database": "ReportingPayments",
      "schema": "dbo",
      "table": "Payments",
      "rows": 8539173,
      "columns": 26
    },
    {
      "database": "ReportingApplications",
      "schema": "dbo",
      "table": "Flags",
      "rows": 7806698,
      "columns": 11
    },
    {
      "database": "ReportingLoanbook",
      "schema": "dbo",
      "table": "Payment_Schedule",
      "rows": 7761998,
      "columns": 7
    },
    {
      "database": "ReportingCentralCrm",
      "schema": "dbo",
      "table": "RobotResponses",
      "rows": 5329459,
      "columns": 13
    },
    {
      "database": "ReportingCentralCrm",
      "schema": "dbo",
      "table": "TriggeredMessages",
      "rows": 5325101,
      "columns": 10
    },
    {
      "database": "ReportingCreditbuilder",
      "schema": "dbo",
      "table": "Accounts",
      "rows": 3593863,
      "columns": 31
    },
    {
      "database": "ReportingCreditbuilder",
      "schema": "dbo",
      "table": "CustomerContracts",
      "rows": 3240619,
      "columns": 5
    },
    {
      "database": "ReportingBrokers",
      "schema": "dbo",
      "table": "SourceHistories",
      "rows": 2566886,
      "columns": 34
    },
    {
      "database": "ReportingLoanbook",
      "schema": "dbo",
      "table": "AppLoginSuccesses",
      "rows": 2054836,
      "columns": 8
    },
    {
      "database": "Whitebox",
      "schema": "dbo",
      "table": "CreditChecks",
      "rows": 2026361,
      "columns": 13
    },
    {
      "database": "Whitebox",
      "schema": "dbo",
      "table": "BankChecks",
      "rows": 1585031,
      "columns": 34
    },
    {
      "database": "ReportingLoanbook",
      "schema": "dbo",
      "table": "Allocate",
      "rows": 1561744,
      "columns": 5
    },
    {
      "database": "ReportingApplications",
      "schema": "dbo",
      "table": "Audit",
      "rows": 1225128,
      "columns": 9
    },
    {
      "database": "Whitebox",
      "schema": "dbo",
      "table": "WeightedScorecardScoreV4s",
      "rows": 1099343,
      "columns": 34
    },
    {
      "database": "ReportingLoanbook",
      "schema": "dbo",
      "table": "CustomFlags",
      "rows": 859811,
      "columns": 22
    },
    {
      "database": "ReportingCommunications",
      "schema": "dbo",
      "table": "ShortUrlClicks",
      "rows": 828784,
      "columns": 4
    },
    {
      "database": "ReportingCentralCrm",
      "schema": "dbo",
      "table": "SentCampaigns",
      "rows": 734178,
      "columns": 7
    },
    {
      "database": "Whitebox",
      "schema": "dbo",
      "table": "VeriffIDs",
      "rows": 626785,
      "columns": 22
    },
    {
      "database": "Whitebox",
      "schema": "dbo",
      "table": "WeightedScorecardScoreV3s",
      "rows": 584571,
      "columns": 29
    },
    {
      "database": "ReportingLookup",
      "schema": "dbo",
      "table": "EmailLookups",
      "rows": 380326,
      "columns": 9
    },
    {
      "database": "ReportingLoanbook",
      "schema": "dbo",
      "table": "Telephones",
      "rows": 378502,
      "columns": 5
    },
    {
      "database": "ReportingLoanbook",
      "schema": "dbo",
      "table": "GovernmentIdentities",
      "rows": 350745,
      "columns": 4
    },
    {
      "database": "ReportingLoanbook",
      "schema": "dbo",
      "table": "Emails",
      "rows": 345380,
      "columns": 5
    },
    {
      "database": "ReportingLoanbook",
      "schema": "dbo",
      "table": "Customer",
      "rows": 311074,
      "columns": 17
    },
    {
      "database": "ReportingApplications",
      "schema": "dbo",
      "table": "VerbalContracts",
      "rows": 249238,
      "columns": 16
    },
    {
      "database": "ReportingCommunications",
      "schema": "dbo",
      "table": "TwilioPhones",
      "rows": 234171,
      "columns": 4
    },
    {
      "database": "Whitebox",
      "schema": "dbo",
      "table": "WeightedScorecardScoreV2s",
      "rows": 224074,
      "columns": 29
    },
    {
      "database": "Whitebox",
      "schema": "dbo",
      "table": "ComplyAdvantages",
      "rows": 192920,
      "columns": 8
    },
    {
      "database": "ReportingPayments",
      "schema": "dbo",
      "table": "Audit",
      "rows": 191259,
      "columns": 10
    },
    {
      "database": "ReportingLoanbook",
      "schema": "dbo",
      "table": "LoanAtInception",
      "rows": 155615,
      "columns": 37
    },
    {
      "database": "ReportingLoanbook",
      "schema": "dbo",
      "table": "Loan",
      "rows": 155615,
      "columns": 40
    },
    {
      "database": "Whitebox",
      "schema": "dbo",
      "table": "UnderwritingScorecardScores",
      "rows": 146301,
      "columns": 31
    },
    {
      "database": "Whitebox",
      "schema": "dbo",
      "table": "WeightedScorecardScores",
      "rows": 132131,
      "columns": 50
    },
    {
      "database": "Whitebox",
      "schema": "dbo",
      "table": "SeonDeviceSessions",
      "rows": 112056,
      "columns": 6
    },
    {
      "database": "ReportingCentralCrm",
      "schema": "dbo",
      "table": "PaymentFactoryRuns",
      "rows": 110126,
      "columns": 8
    },
    {
      "database": "Whitebox",
      "schema": "dbo",
      "table": "OverriddenTasks",
      "rows": 104641,
      "columns": 8
    },
    {
      "database": "Whitebox",
      "schema": "reporting",
      "table": "scorecard2026loans",
      "rows": 84393,
      "columns": 17
    },
    {
      "database": "Whitebox",
      "schema": "reporting",
      "table": "scorecard2026data",
      "rows": 84393,
      "columns": 125
    },
    {
      "database": "Whitebox",
      "schema": "reporting",
      "table": "scorecard2025data",
      "rows": 76763,
      "columns": 125
    },
    {
      "database": "Whitebox",
      "schema": "reporting",
      "table": "scorecard2025loans",
      "rows": 76763,
      "columns": 17
    },
    {
      "database": "ReportingLoanbook",
      "schema": "dbo",
      "table": "PaymentScheduleChanges",
      "rows": 73991,
      "columns": 5
    },
    {
      "database": "ReportingLoanbook",
      "schema": "reporting",
      "table": "oldbookmatch",
      "rows": 66226,
      "columns": 3
    },
    {
      "database": "ReportingApplications",
      "schema": "dbo",
      "table": "SourceReference2Stats",
      "rows": 63001,
      "columns": 9
    },
    {
      "database": "Whitebox",
      "schema": "dbo",
      "table": "RelationshipChecks",
      "rows": 60673,
      "columns": 6
    },
    {
      "database": "ReportingLoanbook",
      "schema": "dbo",
      "table": "DefaultHistory",
      "rows": 52096,
      "columns": 6
    },
    {
      "database": "Whitebox",
      "schema": "dbo",
      "table": "REAPI_AddressData",
      "rows": 48442,
      "columns": 10
    },
    {
      "database": "ReportingPayments",
      "schema": "dbo",
      "table": "PaymentPermissions",
      "rows": 40186,
      "columns": 7
    },
    {
      "database": "ReportingLoanbook",
      "schema": "dbo",
      "table": "Audit",
      "rows": 38517,
      "columns": 9
    },
    {
      "database": "Whitebox",
      "schema": "dbo",
      "table": "ProofOfHomeownerships",
      "rows": 12016,
      "columns": 10
    },
    {
      "database": "Whitebox",
      "schema": "dbo",
      "table": "SeonChecks",
      "rows": 11934,
      "columns": 9
    },
    {
      "database": "ReportingCentralCrm",
      "schema": "dbo",
      "table": "RobotResponderAudits",
      "rows": 7482,
      "columns": 4
    },
    {
      "database": "ReportingLoanbook",
      "schema": "dbo",
      "table": "Flags",
      "rows": 6140,
      "columns": 13
    },
    {
      "database": "ReportingCentralCrm",
      "schema": "dbo",
      "table": "Campaigns",
      "rows": 6078,
      "columns": 20
    },
    {
      "database": "Whitebox",
      "schema": "dbo",
      "table": "DeclineOverrides",
      "rows": 5918,
      "columns": 8
    },
    {
      "database": "Whitebox",
      "schema": "dbo",
      "table": "DirectIdBankStatements",
      "rows": 4380,
      "columns": 3
    },
    {
      "database": "Whitebox",
      "schema": "dbo",
      "table": "DirectIdAccountDetails",
      "rows": 4270,
      "columns": 3
    },
    {
      "database": "Whitebox",
      "schema": "dbo",
      "table": "MlaChecks",
      "rows": 4202,
      "columns": 7
    },
    {
      "database": "Whitebox",
      "schema": "dbo",
      "table": "DirectIds",
      "rows": 3978,
      "columns": 24
    },
    {
      "database": "ReportingBrokers",
      "schema": "dbo",
      "table": "SourceRefs",
      "rows": 3823,
      "columns": 3
    },
    {
      "database": "ReportingBrokers",
      "schema": "dbo",
      "table": "ExcludedRefs",
      "rows": 3765,
      "columns": 9
    },
    {
      "database": "Whitebox",
      "schema": "dbo",
      "table": "BankStatements",
      "rows": 2695,
      "columns": 18
    },
    {
      "database": "ReportingLookup",
      "schema": "dbo",
      "table": "Carriers",
      "rows": 2646,
      "columns": 5
    },
    {
      "database": "Whitebox",
      "schema": "dbo",
      "table": "CheckTasks",
      "rows": 2618,
      "columns": 13
    },
    {
      "database": "Whitebox",
      "schema": "dbo",
      "table": "PlaidChecks",
      "rows": 1943,
      "columns": 14
    },
    {
      "database": "ReportingCentralCrm",
      "schema": "dbo",
      "table": "CannedMessages",
      "rows": 1396,
      "columns": 15
    },
    {
      "database": "ReportingApplications",
      "schema": "dbo",
      "table": "PayoutAllocationHistories",
      "rows": 1149,
      "columns": 7
    }
  ]
}